fastrobots-0.3.0.dist-info/METADATA
fastrobots-0.3.0.dist-info/WHEEL
fastrobots-0.3.0.dist-info/entry_points.txt
fastrobots-0.3.0.dist-info/licenses/LICENSE
fastrobots/__init__.py
fastrobots/_core.cpython-312-x86_64-linux-gnu.so
fastrobots/_core.pyi
fastrobots/cache.py
fastrobots/cli.py
fastrobots/client.py
fastrobots-0.3.0.dist-info/RECORD
