Metadata-Version: 2.4
Name: fastrobots
Version: 0.3.0
Classifier: Development Status :: 4 - Beta
Classifier: Intended Audience :: Developers
Classifier: Topic :: Internet :: WWW/HTTP
Classifier: Topic :: Software Development :: Libraries :: Python Modules
Classifier: Topic :: Text Processing :: Markup :: HTML
Classifier: Programming Language :: Rust
Classifier: Programming Language :: Python :: Implementation :: CPython
Classifier: Programming Language :: Python :: 3
Classifier: Programming Language :: Python :: 3.10
Classifier: Programming Language :: Python :: 3.11
Classifier: Programming Language :: Python :: 3.12
Classifier: Programming Language :: Python :: 3.13
Classifier: License :: OSI Approved :: MIT License
Classifier: Operating System :: POSIX :: Linux
Classifier: Operating System :: MacOS
Classifier: Operating System :: Microsoft :: Windows
Requires-Dist: httpx>=0.28.1
Requires-Dist: click>=8.1.0
License-File: LICENSE
Summary: Blazingly fast robots.txt parser written in Rust - 6x faster than reppy
Keywords: robots.txt,robots,crawler,scraper,web-crawler,seo,parser,rust,fast,reppy
Author-email: Sekinal <business@irvingernesto.com>
License: MIT
Requires-Python: >=3.10
Project-URL: Homepage, https://github.com/sekinal/fastrobots
Project-URL: Repository, https://github.com/sekinal/fastrobots
Project-URL: Issues, https://github.com/sekinal/fastrobots/issues
